odoo/addons/delivery_schenker_quant_package_dimension/README.rst
odoo/addons/delivery_schenker_quant_package_dimension/__init__.py
odoo/addons/delivery_schenker_quant_package_dimension/__manifest__.py
odoo/addons/delivery_schenker_quant_package_dimension/i18n/delivery_schenker_quant_package_dimension.pot
odoo/addons/delivery_schenker_quant_package_dimension/i18n/it.po
odoo/addons/delivery_schenker_quant_package_dimension/models/__init__.py
odoo/addons/delivery_schenker_quant_package_dimension/models/delivery_carrier.py
odoo/addons/delivery_schenker_quant_package_dimension/readme/CONTRIBUTORS.rst
odoo/addons/delivery_schenker_quant_package_dimension/readme/DESCRIPTION.rst
odoo/addons/delivery_schenker_quant_package_dimension/static/description/icon.png
odoo/addons/delivery_schenker_quant_package_dimension/static/description/index.html
odoo/addons/delivery_schenker_quant_package_dimension/tests/__init__.py
odoo/addons/delivery_schenker_quant_package_dimension/tests/test_delivery_schenker.py
odoo14_addon_delivery_schenker_quant_package_dimension-14.0.2.0.1.dist-info/METADATA
odoo14_addon_delivery_schenker_quant_package_dimension-14.0.2.0.1.dist-info/WHEEL
odoo14_addon_delivery_schenker_quant_package_dimension-14.0.2.0.1.dist-info/top_level.txt
odoo14_addon_delivery_schenker_quant_package_dimension-14.0.2.0.1.dist-info/RECORD
