Metadata-Version: 2.1
Name: odoo14-addon-delivery_schenker_quant_package_dimension
Version: 14.0.2.0.1
Summary: Glue module between delivery_schenker and stock_quant_package_dimensionWith this module the transmitted package volume is changed,it uses the computed volume from stock_quant_package_dimension.Also the dimensions length, width and height of a package getting added to the request
Home-page: https://github.com/OCA/delivery-carrier
Author: MT Software, Odoo Community Association (OCA)
Author-email: support@odoo-community.org
License: AGPL-3
Classifier: Programming Language :: Python
Classifier: Framework :: Odoo
Classifier: Framework :: Odoo :: 14.0
Classifier: License :: OSI Approved :: GNU Affero General Public License v3
Requires-Python: >=3.6
Requires-Dist: odoo14-addon-delivery-schenker
Requires-Dist: odoo14-addon-stock-quant-package-dimension
Requires-Dist: odoo<14.1dev,>=14.0a
